LICENSE
MANIFEST.in
README
setup.py
bin/ligo_data_find
bin/ligolw_add
bin/ligolw_combine_segments
bin/ligolw_cut
bin/ligolw_diff
bin/ligolw_print
bin/ligolw_print_tables
bin/ligolw_segment_diff
bin/ligolw_segment_intersect
bin/ligolw_segment_query
bin/ligolw_segment_union
bin/ligolw_segments_from_cats
bin/ligolw_sqlite
etc/ligolw.js
etc/ligolw.xsl
etc/ligolw_dtd.txt
glue/LDBDClient.py
glue/LDBDWClient.py
glue/__init__.py
glue/datafind.py
glue/git_version.py
glue/gpstime.py
glue/iterutils.py
glue/lal.py
glue/ldbd.py
glue/markup.py
glue/offsetvector.py
glue/pidfile.py
glue/pipeline.py
glue/segments.py
glue/segmentsUtils.py
glue/text_progress_bar.py
glue/utils.py
glue/auth/__init__.py
glue/auth/saml.py
glue/ligolw/__init__.py
glue/ligolw/array.py
glue/ligolw/dbtables.py
glue/ligolw/ilwd.c
glue/ligolw/ilwd.h
glue/ligolw/ilwd.py
glue/ligolw/ligolw.py
glue/ligolw/lsctables.py
glue/ligolw/param.py
glue/ligolw/table.py
glue/ligolw/tokenizer.RowBuilder.c
glue/ligolw/tokenizer.RowDumper.c
glue/ligolw/tokenizer.Tokenizer.c
glue/ligolw/tokenizer.c
glue/ligolw/tokenizer.h
glue/ligolw/types.py
glue/ligolw/utils/__init__.py
glue/ligolw/utils/coalesce_db.py
glue/ligolw/utils/coincs.py
glue/ligolw/utils/ligolw_add.py
glue/ligolw/utils/ligolw_sqlite.py
glue/ligolw/utils/print_tables.py
glue/ligolw/utils/process.py
glue/ligolw/utils/search_summary.py
glue/ligolw/utils/segments.py
glue/ligolw/utils/time_slide.py
glue/segmentdb/__init__.py
glue/segmentdb/logic.py
glue/segmentdb/query_engine.py
glue/segmentdb/segmentdb_utils.py
misc/__init__.py
misc/__init__.pyc
misc/generate_vcs_info.py
misc/generate_vcs_info.pyc
misc/git_version.py.in
pycbc_glue.egg-info/PKG-INFO
pycbc_glue.egg-info/SOURCES.txt
pycbc_glue.egg-info/dependency_links.txt
pycbc_glue.egg-info/top_level.txt
src/segments/infinity.c
src/segments/segment.c
src/segments/segmentlist.c
src/segments/segments.c
src/segments/segments.h
test/874000000-20000.cache
test/Makefile
test/demo.xml
test/dq_query_testdoc-800000000-16.xml
test/glue_ligolw_ilwd_verify.py
test/inspiral_event_id_test_in1.xml.gz
test/inspiral_event_id_test_in2.xml
test/iterutils_verify.py
