Metadata-Version: 1.0
Name: pycbc-glue
Version: 0.9.8
Summary: Grid LSC User Engine
Home-page: https://github.com/ligo-cbc/pycbc-glue
Author: Duncan Brown
Author-email: duncan.brown@ligo.org
License: See file LICENSE
Download-URL: https://github.com/ligo-cbc/pycbc-glue/archive/v0.9.8.tar.gz
Platform: UNKNOWN
